X2016NianJiqiZhixinGaofenJishuWenzhangQuanji/README.md
X2016NianJiqiZhixinGaofenJishuWenzhangQuanji/__init__.py
X2016NianJiqiZhixinGaofenJishuWenzhangQuanji/__main__.py
X2016NianJiqiZhixinGaofenJishuWenzhangQuanji/file.epub
X2016NianJiqiZhixinGaofenJishuWenzhangQuanji/index.html
X2016NianJiqiZhixinGaofenJishuWenzhangQuanji/css/__init__.py
X2016NianJiqiZhixinGaofenJishuWenzhangQuanji/css/annotations.css
X2016NianJiqiZhixinGaofenJishuWenzhangQuanji/css/main.css
X2016NianJiqiZhixinGaofenJishuWenzhangQuanji/css/normalize.css
X2016NianJiqiZhixinGaofenJishuWenzhangQuanji/css/popup.css
X2016NianJiqiZhixinGaofenJishuWenzhangQuanji/font/__init__.py
X2016NianJiqiZhixinGaofenJishuWenzhangQuanji/font/fontello.eot
X2016NianJiqiZhixinGaofenJishuWenzhangQuanji/font/fontello.svg
X2016NianJiqiZhixinGaofenJishuWenzhangQuanji/font/fontello.ttf
X2016NianJiqiZhixinGaofenJishuWenzhangQuanji/font/fontello.woff
X2016NianJiqiZhixinGaofenJishuWenzhangQuanji/img/__init__.py
X2016NianJiqiZhixinGaofenJishuWenzhangQuanji/img/annotator-glyph-sprite.png
X2016NianJiqiZhixinGaofenJishuWenzhangQuanji/img/annotator-icon-sprite.png
X2016NianJiqiZhixinGaofenJishuWenzhangQuanji/img/apple-touch-icon.png
X2016NianJiqiZhixinGaofenJishuWenzhangQuanji/img/cancelfullscreen.png
X2016NianJiqiZhixinGaofenJishuWenzhangQuanji/img/close.png
X2016NianJiqiZhixinGaofenJishuWenzhangQuanji/img/fullscreen.png
X2016NianJiqiZhixinGaofenJishuWenzhangQuanji/img/loader.gif
X2016NianJiqiZhixinGaofenJishuWenzhangQuanji/img/menu-icon.png
X2016NianJiqiZhixinGaofenJishuWenzhangQuanji/img/save.png
X2016NianJiqiZhixinGaofenJishuWenzhangQuanji/img/saved.png
X2016NianJiqiZhixinGaofenJishuWenzhangQuanji/img/settings-s.png
X2016NianJiqiZhixinGaofenJishuWenzhangQuanji/img/settings.png
X2016NianJiqiZhixinGaofenJishuWenzhangQuanji/img/star.png
X2016NianJiqiZhixinGaofenJishuWenzhangQuanji/js/__init__.py
X2016NianJiqiZhixinGaofenJishuWenzhangQuanji/js/epub.js
X2016NianJiqiZhixinGaofenJishuWenzhangQuanji/js/epub.min.js
x2016_nian_jiqi_zhixin_gaofen_jishu_wenzhang_quanji-2024.3.3.0.dist-info/METADATA
x2016_nian_jiqi_zhixin_gaofen_jishu_wenzhang_quanji-2024.3.3.0.dist-info/WHEEL
x2016_nian_jiqi_zhixin_gaofen_jishu_wenzhang_quanji-2024.3.3.0.dist-info/entry_points.txt
x2016_nian_jiqi_zhixin_gaofen_jishu_wenzhang_quanji-2024.3.3.0.dist-info/top_level.txt
x2016_nian_jiqi_zhixin_gaofen_jishu_wenzhang_quanji-2024.3.3.0.dist-info/RECORD
